mlshed/__init__.py
mlshed/_version.py
mlshed/azure.py
mlshed/cfg.py
mlshed/exceptions.py
mlshed/model.py
mlshed-0.0.4.dist-info/METADATA
mlshed-0.0.4.dist-info/RECORD
mlshed-0.0.4.dist-info/WHEEL
mlshed-0.0.4.dist-info/top_level.txt
tests/__init__.py
tests/test_basics.py
