Metadata-Version: 2.1
Name: mlshed
Version: 0.0.4
Summary: Simple local/remote machine learning model store for Python.
Home-page: https://github.com/shaypal5/mlshed
Author: Shay Palachy
Author-email: shay.palachy@gmail.com
License: UNKNOWN
Platform: UNKNOWN
Classifier: Development Status :: 4 - Beta
Classifier: Intended Audience :: Developers
Classifier: Natural Language :: English
Classifier: License :: OSI Approved :: MIT License
Classifier: Programming Language :: Python
Classifier: Programming Language :: Python :: 3
Classifier: Programming Language :: Python :: 3.4
Classifier: Programming Language :: Python :: 3.5
Classifier: Programming Language :: Python :: 3.6
Classifier: Topic :: Software Development :: Libraries
Classifier: Topic :: Software Development :: Libraries :: Python Modules
Requires-Python: >=3.5
Provides-Extra: test
Requires-Dist: birch (>=0.0.10)
Requires-Dist: azure-storage-blob (==1.3.1)
Requires-Dist: decore (==0.0.1)
Provides-Extra: test
Requires-Dist: pytest; extra == 'test'
Requires-Dist: coverage; extra == 'test'
Requires-Dist: pytest-cov; extra == 'test'
Requires-Dist: collective.checkdocs; extra == 'test'
Requires-Dist: pygments; extra == 'test'
Requires-Dist: birch (>=0.0.10); extra == 'test'
Requires-Dist: azure-storage-blob (==1.3.1); extra == 'test'
Requires-Dist: decore (==0.0.1); extra == 'test'
